grids/__init__.py
grids/_consts.py
grids/_coords.py
grids/_errors.py
grids/_ts.py
grids/_utils.py
grids-0.15.dist-info/LICENSE
grids-0.15.dist-info/METADATA
grids-0.15.dist-info/WHEEL
grids-0.15.dist-info/top_level.txt
grids-0.15.dist-info/RECORD
