Metadata-Version: 2.1
Name: grids
Version: 0.15
Summary: Tools for extracting time series subsets from n-dimensional arrays in several storage formats.
Home-page: UNKNOWN
Author: Riley Hales
License: BSD 3-Clause Clear
Platform: UNKNOWN
Classifier: Development Status :: 5 - Production/Stable
Classifier: Programming Language :: Python :: 3
Classifier: Topic :: Scientific/Engineering :: GIS
Classifier: Topic :: Scientific/Engineering :: Information Analysis
Classifier: Intended Audience :: Science/Research
Classifier: License :: OSI Approved :: BSD License
Classifier: Natural Language :: English
Classifier: Operating System :: OS Independent
Requires-Python: >=3
License-File: LICENSE
Requires-Dist: affine
Requires-Dist: cfgrib
Requires-Dist: eccodes
Requires-Dist: geopandas
Requires-Dist: h5py
Requires-Dist: netcdf4
Requires-Dist: numpy
Requires-Dist: pandas
Requires-Dist: pydap
Requires-Dist: python-dateutil
Requires-Dist: rasterio
Requires-Dist: requests
Requires-Dist: xarray
Provides-Extra: pygrib
Requires-Dist: pyproj ; extra == 'pygrib'
Requires-Dist: pygrib ; extra == 'pygrib'
